[
  {
    "id": "fishermans-forgotten-friend",
    "title": "Fishermans Forgotten Friend",
    "description": "",
    "filename": "landscapes/fishermans-forgotten-friend.jpg",
    "date": "",
    "location": ""
  },
  {
    "id": "hallin-fell",
    "title": "Hallin Fell",
    "description": "",
    "filename": "landscapes/hallin-fell.jpg",
    "date": "",
    "location": ""
  },
  {
    "id": "helping-hand",
    "title": "Helping Hand",
    "description": "",
    "filename": "landscapes/helping-hand.jpg",
    "date": "",
    "location": ""
  },
  {
    "id": "hotizon-on-fire",
    "title": "Hotizon On Fire",
    "description": "",
    "filename": "landscapes/hotizon-on-fire.jpg",
    "date": "",
    "location": ""
  },
  {
    "id": "into-the-mist",
    "title": "Into The Mist",
    "description": "",
    "filename": "landscapes/into-the-mist.jpg",
    "date": "",
    "location": ""
  },
  {
    "id": "leaves",
    "title": "Leaves",
    "description": "",
    "filename": "landscapes/leaves.jpg",
    "date": "",
    "location": ""
  },
  {
    "id": "misty-fells",
    "title": "Misty Fells",
    "description": "",
    "filename": "landscapes/misty-fells.jpg",
    "date": "",
    "location": ""
  },
  {
    "id": "mixed-media",
    "title": "Mixed Media",
    "description": "",
    "filename": "landscapes/mixed-media.jpg",
    "date": "",
    "location": ""
  },
  {
    "id": "perched-on-the-edge",
    "title": "Perched On The Edge",
    "description": "",
    "filename": "landscapes/perched-on-the-edge.jpg",
    "date": "",
    "location": ""
  },
  {
    "id": "sheepish-silhouette",
    "title": "Sheepish Silhouette",
    "description": "",
    "filename": "landscapes/sheepish-silhouette.jpg",
    "date": "",
    "location": ""
  },
  {
    "id": "standing-before-the-stand",
    "title": "Standing Before The Stand",
    "description": "",
    "filename": "landscapes/standing-before-the-stand.jpg",
    "date": "",
    "location": ""
  },
  {
    "id": "twin-trees",
    "title": "Twin Trees",
    "description": "",
    "filename": "landscapes/twin-trees.jpg",
    "date": "",
    "location": ""
  },
  {
    "id": "twisted-trees",
    "title": "Twisted Trees",
    "description": "",
    "filename": "landscapes/twisted-trees.jpg",
    "date": "",
    "location": ""
  },
  {
    "id": "ullswater-vista",
    "title": "Ullswater Vista",
    "description": "",
    "filename": "landscapes/ullswater-vista.jpg",
    "date": "",
    "location": ""
  },
  {
    "id": "yfirgefnar",
    "title": "Yfirgefnar",
    "description": "",
    "filename": "landscapes/yfirgefnar.jpg",
    "date": "",
    "location": ""
  }
]
