[
  {
    "id": "belper-mill-bridge",
    "title": "Belper Mill Bridge",
    "description": "",
    "filename": "nightscapes/belper-mill-bridge.jpg",
    "date": "",
    "location": ""
  },
  {
    "id": "circles",
    "title": "Circles",
    "description": "",
    "filename": "nightscapes/circles.jpg",
    "date": "",
    "location": ""
  },
  {
    "id": "eosophobia",
    "title": "Eosophobia",
    "description": "",
    "filename": "nightscapes/eosophobia.jpg",
    "date": "",
    "location": ""
  },
  {
    "id": "heage-windmill",
    "title": "Heage Windmill",
    "description": "",
    "filename": "nightscapes/heage-windmill.jpg",
    "date": "",
    "location": ""
  },
  {
    "id": "impending-doom",
    "title": "Impending Doom",
    "description": "",
    "filename": "nightscapes/impending-doom.jpg",
    "date": "",
    "location": ""
  },
  {
    "id": "lakeside",
    "title": "Lakeside",
    "description": "",
    "filename": "nightscapes/lakeside.jpg",
    "date": "",
    "location": ""
  },
  {
    "id": "lunar-eclipse",
    "title": "Lunar Eclipse",
    "description": "",
    "filename": "nightscapes/lunar-eclipse.jpg",
    "date": "",
    "location": ""
  },
  {
    "id": "stainsby-06",
    "title": "Stainsby 06",
    "description": "",
    "filename": "nightscapes/stainsby-06.jpg",
    "date": "",
    "location": ""
  },
  {
    "id": "star-disk",
    "title": "Star Disk",
    "description": "",
    "filename": "nightscapes/star-disk.jpg",
    "date": "",
    "location": ""
  },
  {
    "id": "star-gazer",
    "title": "Star Gazer",
    "description": "",
    "filename": "nightscapes/star-gazer.jpg",
    "date": "",
    "location": ""
  },
  {
    "id": "summer-solstace",
    "title": "Summer Solstace",
    "description": "",
    "filename": "nightscapes/summer-solstace.jpg",
    "date": "",
    "location": ""
  },
  {
    "id": "trapped",
    "title": "Trapped",
    "description": "",
    "filename": "nightscapes/trapped.jpg",
    "date": "",
    "location": ""
  }
]
